anco/__init__.py
anco/target.py
anco/utils.py
anco-1.1.0.dist-info/LICENSE
anco-1.1.0.dist-info/METADATA
anco-1.1.0.dist-info/WHEEL
anco-1.1.0.dist-info/top_level.txt
anco-1.1.0.dist-info/RECORD
